octowebsocket/__init__.py
octowebsocket/_abnf.py
octowebsocket/_app.py
octowebsocket/_cookiejar.py
octowebsocket/_core.py
octowebsocket/_exceptions.py
octowebsocket/_handshake.py
octowebsocket/_http.py
octowebsocket/_logging.py
octowebsocket/_socket.py
octowebsocket/_ssl_compat.py
octowebsocket/_url.py
octowebsocket/_utils.py
octowebsocket/_wsdump.py
octowebsocket/py.typed
octowebsocket/tests/__init__.py
octowebsocket/tests/echo-server.py
octowebsocket/tests/test_abnf.py
octowebsocket/tests/test_app.py
octowebsocket/tests/test_cookiejar.py
octowebsocket/tests/test_http.py
octowebsocket/tests/test_url.py
octowebsocket/tests/test_websocket.py
octowebsocket_client-1.8.3.dist-info/LICENSE
octowebsocket_client-1.8.3.dist-info/METADATA
octowebsocket_client-1.8.3.dist-info/WHEEL
octowebsocket_client-1.8.3.dist-info/entry_points.txt
octowebsocket_client-1.8.3.dist-info/top_level.txt
octowebsocket_client-1.8.3.dist-info/RECORD
