Metadata-Version: 2.1
Name: octowebsocket-client
Version: 1.8.3
Summary: WebSocket client for Python with low level API options for OctoEverywhere.com and Homeway.io
Home-page: https://github.com/OctoEverywhere/octowebsocket-client.git
Download-URL: https://github.com/OctoEverywhere/octowebsocket-client/releases
Author: liris
Author-email: liris.pp@gmail.com
Maintainer: quinndamerell
Maintainer-email: support@octoeverywhere.com
License: Apache-2.0
Project-URL: Documentation, https://websocket-client.readthedocs.io/
Project-URL: Source, https://github.com/OctoEverywhere/octowebsocket-client
Keywords: octoeverywhere homeway
Classifier: Development Status :: 5 - Production/Stable
Classifier: License :: OSI Approved :: Apache Software License
Classifier: Programming Language :: Python :: 3
Classifier: Programming Language :: Python :: 3.7
Classifier: Programming Language :: Python :: 3.8
Classifier: Programming Language :: Python :: 3.9
Classifier: Programming Language :: Python :: 3.10
Classifier: Programming Language :: Python :: 3.11
Classifier: Programming Language :: Python :: 3.12
Classifier: Operating System :: MacOS :: MacOS X
Classifier: Operating System :: POSIX
Classifier: Operating System :: Microsoft :: Windows
Classifier: Topic :: Internet
Classifier: Topic :: Software Development :: Libraries :: Python Modules
Classifier: Intended Audience :: Developers
Requires-Python: >=3.7
License-File: LICENSE
Provides-Extra: docs
Requires-Dist: Sphinx >=6.0 ; extra == 'docs'
Requires-Dist: sphinx-rtd-theme >=1.1.0 ; extra == 'docs'
Requires-Dist: myst-parser >=2.0.0 ; extra == 'docs'
Provides-Extra: optional
Requires-Dist: python-socks ; extra == 'optional'
Requires-Dist: wsaccel ; extra == 'optional'
Provides-Extra: test
Requires-Dist: websockets ; extra == 'test'
